<annotation>
	<folder>training_data_YOLO</folder>
	<filename>1278.png</filename>
	<path>/Users/nitipongchanglor/MLis2_Notebook/train_test_data/training_data_YOLO/1278.png</path>
	<source>
		<database>Unknown</database>
	</source>
	<size>
		<width>320</width>
		<height>240</height>
		<depth>3</depth>
	</size>
	<segmented>0</segmented>
	<object>
		<name>left</name>
		<pose>Unspecified</pose>
		<truncated>0</truncated>
		<difficult>0</difficult>
		<bndbox>
			<xmin>132</xmin>
			<ymin>24</ymin>
			<xmax>158</xmax>
			<ymax>35</ymax>
		</bndbox>
	</object>
	<object>
		<name>left</name>
		<pose>Unspecified</pose>
		<truncated>0</truncated>
		<difficult>0</difficult>
		<bndbox>
			<xmin>172</xmin>
			<ymin>24</ymin>
			<xmax>198</xmax>
			<ymax>38</ymax>
		</bndbox>
	</object>
	<object>
		<name>left</name>
		<pose>Unspecified</pose>
		<truncated>0</truncated>
		<difficult>0</difficult>
		<bndbox>
			<xmin>205</xmin>
			<ymin>24</ymin>
			<xmax>228</xmax>
			<ymax>38</ymax>
		</bndbox>
	</object>
</annotation>
